yaz_messaging_plugin/__init__.py
yaz_messaging_plugin/loader.py
yaz_messaging_plugin/log.py
yaz_messaging_plugin/messaging.py
yaz_messaging_plugin/version.py
yaz_messaging_plugin-1.2.0.data/scripts/yaz-messaging
yaz_messaging_plugin-1.2.0.dist-info/METADATA
yaz_messaging_plugin-1.2.0.dist-info/WHEEL
yaz_messaging_plugin-1.2.0.dist-info/top_level.txt
yaz_messaging_plugin-1.2.0.dist-info/RECORD
