Metadata-Version: 2.1
Name: yaz-messaging-plugin
Version: 1.2.0
Summary: A symfony message translation plugin for YAZ
Home-page: http://github.com/yaz/yaz_messaging_plugin
Author: Boudewijn Schoon
Author-email: boudewijn@zicht.nl
License: MIT
Platform: UNKNOWN
Classifier: Development Status :: 4 - Beta
Classifier: Environment :: Console
Classifier: License :: OSI Approved :: MIT License
Classifier: Programming Language :: Python :: 3.6
Requires-Dist: google-cloud-translate
Requires-Dist: pyyaml
Requires-Dist: yaz
